[{"child_stop_id": "2576", "route_id": "56-10647", "route_code": "56", "service_id": "2023-COMBNXT-Weekday-10", "arrival_time": "PT15H31M0S", "departure_time": "PT15H31M0S", "heading": "City", "sequence": 32, "accessibility": {"bikesAllowed": "allowed", "wheelchairAccessible": "accessible"}}, {"child_stop_id": "2576", "route_id": "56-10647", "route_code": "56", "service_id": "2023-COMBNXT-Weekday-10", "arrival_time": "PT8H46M0S", "departure_time": "PT8H46M0S", "heading": "Fyshwick", "sequence": 27, "accessibility": {"bikesAllowed": "allowed", "wheelchairAccessible": "accessible"}}, {"child_stop_id": "2576", "route_id": "56-10647", "route_code": "56", "service_id": "2023-COMBNXT-Weekday-10", "arrival_time": "PT8H50M0S", "departure_time": "PT8H50M0S", "heading": "City", "sequence": 32, "accessibility": {"bikesAllowed": "allowed", "wheelchairAccessible": "accessible"}}, {"child_stop_id": "2576", "route_id": "56-10647", "route_code": "56", "service_id": "2023-COMBNXT-Weekday-10", "arrival_time": "PT15H30M0S", "departure_time": "PT15H30M0S", "heading": "Fyshwick", "sequence": 27, "accessibility": {"bikesAllowed": "allowed", "wheelchairAccessible": "accessible"}}]