[{"child_stop_id": "4240", "route_id": "42-10647", "route_code": "42", "service_id": "2023-COMBNXT-Weekday-10", "arrival_time": "PT15H33M0S", "departure_time": "PT15H33M0S", "heading": "Fraser Loop", "sequence": 39, "accessibility": {"bikesAllowed": "allowed", "wheelchairAccessible": "accessible"}}, {"child_stop_id": "4240", "route_id": "42-10647", "route_code": "42", "service_id": "2023-COMBNXT-Weekday-10", "arrival_time": "PT17H3M0S", "departure_time": "PT17H3M0S", "heading": "Fraser Loop", "sequence": 39, "accessibility": {"bikesAllowed": "allowed", "wheelchairAccessible": "accessible"}}, {"child_stop_id": "4240", "route_id": "42-10647", "route_code": "42", "service_id": "2023-COMBNXT-Weekday-10", "arrival_time": "PT11H1M0S", "departure_time": "PT11H1M0S", "heading": "Fraser Loop", "sequence": 39, "accessibility": {"bikesAllowed": "allowed", "wheelchairAccessible": "accessible"}}, {"child_stop_id": "4240", "route_id": "42-10647", "route_code": "42", "service_id": "2023-COMBNXT-Weekday-10", "arrival_time": "PT12H1M0S", "departure_time": "PT12H1M0S", "heading": "Fraser Loop", "sequence": 39, "accessibility": {"bikesAllowed": "allowed", "wheelchairAccessible": "accessible"}}, {"child_stop_id": "4240", "route_id": "42-10647", "route_code": "42", "service_id": "2023-COMBNXT-Weekday-10", "arrival_time": "PT16H3M0S", "departure_time": "PT16H3M0S", "heading": "Fraser Loop", "sequence": 39, "accessibility": {"bikesAllowed": "allowed", "wheelchairAccessible": "accessible"}}, {"child_stop_id": "4240", "route_id": "42-10647", "route_code": "42", "service_id": "2023-COMBNXT-Weekday-10", "arrival_time": "PT15H3M0S", "departure_time": "PT15H3M0S", "heading": "Fraser Loop", "sequence": 39, "accessibility": {"bikesAllowed": "allowed", "wheelchairAccessible": "accessible"}}, {"child_stop_id": "4240", "route_id": "42-10647", "route_code": "42", "service_id": "2023-COMBNXT-Weekday-10", "arrival_time": "PT22H29M0S", "departure_time": "PT22H29M0S", "heading": "Fraser Loop", "sequence": 39, "accessibility": {"bikesAllowed": "allowed", "wheelchairAccessible": "accessible"}}, {"child_stop_id": "4240", "route_id": "42-10647", "route_code": "42", "service_id": "2023-COMBNXT-Weekday-10", "arrival_time": "PT17H33M0S", "departure_time": "PT17H33M0S", "heading": "Fraser Loop", "sequence": 39, "accessibility": {"bikesAllowed": "allowed", "wheelchairAccessible": "accessible"}}, {"child_stop_id": "4240", "route_id": "42-10647", "route_code": "42", "service_id": "2023-COMBNXT-Weekday-10", "arrival_time": "PT16H33M0S", "departure_time": "PT16H33M0S", "heading": "Fraser Loop", "sequence": 39, "accessibility": {"bikesAllowed": "allowed", "wheelchairAccessible": "accessible"}}, {"child_stop_id": "4240", "route_id": "42-10647", "route_code": "42", "service_id": "2023-COMBNXT-Weekday-10", "arrival_time": "PT14H1M0S", "departure_time": "PT14H1M0S", "heading": "Fraser Loop", "sequence": 39, "accessibility": {"bikesAllowed": "allowed", "wheelchairAccessible": "accessible"}}, {"child_stop_id": "4240", "route_id": "42-10647", "route_code": "42", "service_id": "2023-COMBNXT-Weekday-10", "arrival_time": "PT19H29M0S", "departure_time": "PT19H29M0S", "heading": "Fraser Loop", "sequence": 39, "accessibility": {"bikesAllowed": "allowed", "wheelchairAccessible": "accessible"}}, {"child_stop_id": "4240", "route_id": "42-10647", "route_code": "42", "service_id": "2023-COMBNXT-Weekday-10", "arrival_time": "PT18H2M0S", "departure_time": "PT18H2M0S", "heading": "Fraser Loop", "sequence": 39, "accessibility": {"bikesAllowed": "unknown", "wheelchairAccessible": "accessible"}}, {"child_stop_id": "4240", "route_id": "42-10647", "route_code": "42", "service_id": "2023-COMBNXT-Weekday-10", "arrival_time": "PT13H31M0S", "departure_time": "PT13H31M0S", "heading": "Fraser Loop", "sequence": 39, "accessibility": {"bikesAllowed": "allowed", "wheelchairAccessible": "accessible"}}, {"child_stop_id": "4240", "route_id": "42-10647", "route_code": "42", "service_id": "2023-COMBNXT-Weekday-10", "arrival_time": "PT14H31M0S", "departure_time": "PT14H31M0S", "heading": "Fraser Loop", "sequence": 39, "accessibility": {"bikesAllowed": "allowed", "wheelchairAccessible": "accessible"}}, {"child_stop_id": "4240", "route_id": "42-10647", "route_code": "42", "service_id": "2023-COMBNXT-Weekday-10", "arrival_time": "PT13H1M0S", "departure_time": "PT13H1M0S", "heading": "Fraser Loop", "sequence": 39, "accessibility": {"bikesAllowed": "allowed", "wheelchairAccessible": "accessible"}}, {"child_stop_id": "4240", "route_id": "42-10647", "route_code": "42", "service_id": "2023-COMBNXT-Weekday-10", "arrival_time": "PT18H32M0S", "departure_time": "PT18H32M0S", "heading": "Fraser Loop", "sequence": 39, "accessibility": {"bikesAllowed": "unknown", "wheelchairAccessible": "accessible"}}, {"child_stop_id": "4240", "route_id": "42-10647", "route_code": "42", "service_id": "2023-COMBNXT-Weekday-10", "arrival_time": "PT21H29M0S", "departure_time": "PT21H29M0S", "heading": "Fraser Loop", "sequence": 39, "accessibility": {"bikesAllowed": "allowed", "wheelchairAccessible": "accessible"}}, {"child_stop_id": "4240", "route_id": "42-10647", "route_code": "42", "service_id": "2023-COMBNXT-Weekday-10", "arrival_time": "PT12H31M0S", "departure_time": "PT12H31M0S", "heading": "Fraser Loop", "sequence": 39, "accessibility": {"bikesAllowed": "allowed", "wheelchairAccessible": "accessible"}}, {"child_stop_id": "4240", "route_id": "42-10647", "route_code": "42", "service_id": "2023-COMBNXT-Weekday-10", "arrival_time": "PT19H2M0S", "departure_time": "PT19H2M0S", "heading": "Fraser Loop", "sequence": 39, "accessibility": {"bikesAllowed": "allowed", "wheelchairAccessible": "accessible"}}, {"child_stop_id": "4240", "route_id": "42-10647", "route_code": "42", "service_id": "2023-COMBNXT-Weekday-10", "arrival_time": "PT10H1M0S", "departure_time": "PT10H1M0S", "heading": "Fraser Loop", "sequence": 39, "accessibility": {"bikesAllowed": "allowed", "wheelchairAccessible": "accessible"}}, {"child_stop_id": "4240", "route_id": "42-10647", "route_code": "42", "service_id": "2023-COMBNXT-Weekday-10", "arrival_time": "PT10H31M0S", "departure_time": "PT10H31M0S", "heading": "Fraser Loop", "sequence": 39, "accessibility": {"bikesAllowed": "allowed", "wheelchairAccessible": "accessible"}}, {"child_stop_id": "4240", "route_id": "42-10647", "route_code": "42", "service_id": "2023-COMBNXT-Weekday-10", "arrival_time": "PT11H31M0S", "departure_time": "PT11H31M0S", "heading": "Fraser Loop", "sequence": 39, "accessibility": {"bikesAllowed": "unknown", "wheelchairAccessible": "accessible"}}, {"child_stop_id": "4240", "route_id": "42-10647", "route_code": "42", "service_id": "2023-COMBNXT-Weekday-10", "arrival_time": "PT9H30M0S", "departure_time": "PT9H30M0S", "heading": "Fraser Loop", "sequence": 39, "accessibility": {"bikesAllowed": "allowed", "wheelchairAccessible": "accessible"}}, {"child_stop_id": "4240", "route_id": "42-10647", "route_code": "42", "service_id": "2023-COMBNXT-Weekday-10", "arrival_time": "PT20H29M0S", "departure_time": "PT20H29M0S", "heading": "Fraser Loop", "sequence": 39, "accessibility": {"bikesAllowed": "allowed", "wheelchairAccessible": "accessible"}}, {"child_stop_id": "4240", "route_id": "42-10647", "route_code": "42", "service_id": "2023-COMBNXT-Weekday-10", "arrival_time": "PT6H28M0S", "departure_time": "PT6H28M0S", "heading": "Fraser Loop", "sequence": 39, "accessibility": {"bikesAllowed": "allowed", "wheelchairAccessible": "accessible"}}, {"child_stop_id": "4240", "route_id": "42-10647", "route_code": "42", "service_id": "2023-COMBNXT-Weekday-10", "arrival_time": "PT6H58M0S", "departure_time": "PT6H58M0S", "heading": "Fraser Loop", "sequence": 39, "accessibility": {"bikesAllowed": "allowed", "wheelchairAccessible": "accessible"}}, {"child_stop_id": "4240", "route_id": "42-10647", "route_code": "42", "service_id": "2023-COMBNXT-Weekday-10", "arrival_time": "PT7H29M0S", "departure_time": "PT7H29M0S", "heading": "Fraser Loop", "sequence": 39, "accessibility": {"bikesAllowed": "allowed", "wheelchairAccessible": "accessible"}}, {"child_stop_id": "4240", "route_id": "42-10647", "route_code": "42", "service_id": "2023-COMBNXT-Weekday-10", "arrival_time": "PT8H2M0S", "departure_time": "PT8H2M0S", "heading": "Fraser Loop", "sequence": 39, "accessibility": {"bikesAllowed": "allowed", "wheelchairAccessible": "accessible"}}, {"child_stop_id": "4240", "route_id": "42-10647", "route_code": "42", "service_id": "2023-COMBNXT-Weekday-10", "arrival_time": "PT5H58M0S", "departure_time": "PT5H58M0S", "heading": "Fraser Loop", "sequence": 39, "accessibility": {"bikesAllowed": "allowed", "wheelchairAccessible": "accessible"}}, {"child_stop_id": "4240", "route_id": "42-10647", "route_code": "42", "service_id": "2023-COMBNXT-Weekday-10", "arrival_time": "PT8H32M0S", "departure_time": "PT8H32M0S", "heading": "Fraser Loop", "sequence": 39, "accessibility": {"bikesAllowed": "allowed", "wheelchairAccessible": "accessible"}}, {"child_stop_id": "4240", "route_id": "42-10647", "route_code": "42", "service_id": "2023-COMBNXT-Weekday-10", "arrival_time": "PT9H1M0S", "departure_time": "PT9H1M0S", "heading": "Fraser Loop", "sequence": 39, "accessibility": {"bikesAllowed": "allowed", "wheelchairAccessible": "accessible"}}, {"child_stop_id": "4240", "route_id": "42-10647", "route_code": "42", "service_id": "2023-COMBNXT-Saturday-05", "arrival_time": "PT11H3M0S", "departure_time": "PT11H3M0S", "heading": "Fraser Loop", "sequence": 39, "accessibility": {"bikesAllowed": "unknown", "wheelchairAccessible": "inaccessible"}}, {"child_stop_id": "4240", "route_id": "42-10647", "route_code": "42", "service_id": "2023-COMBNXT-Saturday-05", "arrival_time": "PT8H2M0S", "departure_time": "PT8H2M0S", "heading": "Fraser Loop", "sequence": 39, "accessibility": {"bikesAllowed": "unknown", "wheelchairAccessible": "inaccessible"}}, {"child_stop_id": "4240", "route_id": "42-10647", "route_code": "42", "service_id": "2023-COMBNXT-Saturday-05", "arrival_time": "PT18H2M0S", "departure_time": "PT18H2M0S", "heading": "Fraser Loop", "sequence": 39, "accessibility": {"bikesAllowed": "unknown", "wheelchairAccessible": "inaccessible"}}, {"child_stop_id": "4240", "route_id": "42-10647", "route_code": "42", "service_id": "2023-COMBNXT-Saturday-05", "arrival_time": "PT23H32M0S", "departure_time": "PT23H32M0S", "heading": "Fraser Loop", "sequence": 39, "accessibility": {"bikesAllowed": "unknown", "wheelchairAccessible": "inaccessible"}}, {"child_stop_id": "4240", "route_id": "42-10647", "route_code": "42", "service_id": "2023-COMBNXT-Saturday-05", "arrival_time": "PT16H3M0S", "departure_time": "PT16H3M0S", "heading": "Fraser Loop", "sequence": 39, "accessibility": {"bikesAllowed": "unknown", "wheelchairAccessible": "inaccessible"}}, {"child_stop_id": "4240", "route_id": "42-10647", "route_code": "42", "service_id": "2023-COMBNXT-Saturday-05", "arrival_time": "PT21H32M0S", "departure_time": "PT21H32M0S", "heading": "Fraser Loop", "sequence": 39, "accessibility": {"bikesAllowed": "unknown", "wheelchairAccessible": "inaccessible"}}, {"child_stop_id": "4240", "route_id": "42-10647", "route_code": "42", "service_id": "2023-COMBNXT-Saturday-05", "arrival_time": "PT14H3M0S", "departure_time": "PT14H3M0S", "heading": "Fraser Loop", "sequence": 39, "accessibility": {"bikesAllowed": "unknown", "wheelchairAccessible": "inaccessible"}}, {"child_stop_id": "4240", "route_id": "42-10647", "route_code": "42", "service_id": "2023-COMBNXT-Saturday-05", "arrival_time": "PT19H32M0S", "departure_time": "PT19H32M0S", "heading": "Fraser Loop", "sequence": 39, "accessibility": {"bikesAllowed": "unknown", "wheelchairAccessible": "inaccessible"}}, {"child_stop_id": "4240", "route_id": "42-10647", "route_code": "42", "service_id": "2023-COMBNXT-Saturday-05", "arrival_time": "PT12H3M0S", "departure_time": "PT12H3M0S", "heading": "Fraser Loop", "sequence": 39, "accessibility": {"bikesAllowed": "unknown", "wheelchairAccessible": "inaccessible"}}, {"child_stop_id": "4240", "route_id": "42-10647", "route_code": "42", "service_id": "2023-COMBNXT-Saturday-05", "arrival_time": "PT10H3M0S", "departure_time": "PT10H3M0S", "heading": "Fraser Loop", "sequence": 39, "accessibility": {"bikesAllowed": "unknown", "wheelchairAccessible": "inaccessible"}}, {"child_stop_id": "4240", "route_id": "42-10647", "route_code": "42", "service_id": "2023-COMBNXT-Saturday-05", "arrival_time": "PT7H2M0S", "departure_time": "PT7H2M0S", "heading": "Fraser Loop", "sequence": 39, "accessibility": {"bikesAllowed": "unknown", "wheelchairAccessible": "inaccessible"}}, {"child_stop_id": "4240", "route_id": "42-10647", "route_code": "42", "service_id": "2023-COMBNXT-Saturday-05", "arrival_time": "PT9H2M0S", "departure_time": "PT9H2M0S", "heading": "Fraser Loop", "sequence": 39, "accessibility": {"bikesAllowed": "unknown", "wheelchairAccessible": "inaccessible"}}, {"child_stop_id": "4240", "route_id": "42-10647", "route_code": "42", "service_id": "2023-COMBNXT-Saturday-05", "arrival_time": "PT13H3M0S", "departure_time": "PT13H3M0S", "heading": "Fraser Loop", "sequence": 39, "accessibility": {"bikesAllowed": "unknown", "wheelchairAccessible": "inaccessible"}}, {"child_stop_id": "4240", "route_id": "42-10647", "route_code": "42", "service_id": "2023-COMBNXT-Saturday-05", "arrival_time": "PT15H3M0S", "departure_time": "PT15H3M0S", "heading": "Fraser Loop", "sequence": 39, "accessibility": {"bikesAllowed": "unknown", "wheelchairAccessible": "inaccessible"}}, {"child_stop_id": "4240", "route_id": "42-10647", "route_code": "42", "service_id": "2023-COMBNXT-Saturday-05", "arrival_time": "PT17H3M0S", "departure_time": "PT17H3M0S", "heading": "Fraser Loop", "sequence": 39, "accessibility": {"bikesAllowed": "unknown", "wheelchairAccessible": "inaccessible"}}, {"child_stop_id": "4240", "route_id": "42-10647", "route_code": "42", "service_id": "2023-COMBNXT-Sunday-04", "arrival_time": "PT7H32M0S", "departure_time": "PT7H32M0S", "heading": "Fraser Loop", "sequence": 39, "accessibility": {"bikesAllowed": "allowed", "wheelchairAccessible": "accessible"}}, {"child_stop_id": "4240", "route_id": "42-10647", "route_code": "42", "service_id": "2023-COMBNXT-Sunday-04", "arrival_time": "PT9H33M0S", "departure_time": "PT9H33M0S", "heading": "Fraser Loop", "sequence": 39, "accessibility": {"bikesAllowed": "allowed", "wheelchairAccessible": "accessible"}}, {"child_stop_id": "4240", "route_id": "42-10647", "route_code": "42", "service_id": "2023-COMBNXT-Sunday-04", "arrival_time": "PT11H33M0S", "departure_time": "PT11H33M0S", "heading": "Fraser Loop", "sequence": 39, "accessibility": {"bikesAllowed": "allowed", "wheelchairAccessible": "accessible"}}, {"child_stop_id": "4240", "route_id": "42-10647", "route_code": "42", "service_id": "2023-COMBNXT-Sunday-04", "arrival_time": "PT13H33M0S", "departure_time": "PT13H33M0S", "heading": "Fraser Loop", "sequence": 39, "accessibility": {"bikesAllowed": "allowed", "wheelchairAccessible": "accessible"}}, {"child_stop_id": "4240", "route_id": "42-10647", "route_code": "42", "service_id": "2023-COMBNXT-Sunday-04", "arrival_time": "PT15H33M0S", "departure_time": "PT15H33M0S", "heading": "Fraser Loop", "sequence": 39, "accessibility": {"bikesAllowed": "allowed", "wheelchairAccessible": "accessible"}}, {"child_stop_id": "4240", "route_id": "42-10647", "route_code": "42", "service_id": "2023-COMBNXT-Sunday-04", "arrival_time": "PT17H32M0S", "departure_time": "PT17H32M0S", "heading": "Fraser Loop", "sequence": 39, "accessibility": {"bikesAllowed": "allowed", "wheelchairAccessible": "accessible"}}, {"child_stop_id": "4240", "route_id": "42-10647", "route_code": "42", "service_id": "2023-COMBNXT-Sunday-04", "arrival_time": "PT19H32M0S", "departure_time": "PT19H32M0S", "heading": "Fraser Loop", "sequence": 39, "accessibility": {"bikesAllowed": "allowed", "wheelchairAccessible": "accessible"}}, {"child_stop_id": "4240", "route_id": "42-10647", "route_code": "42", "service_id": "2023-COMBVAC-Weekday-05", "arrival_time": "PT5H58M0S", "departure_time": "PT5H58M0S", "heading": "Fraser Loop", "sequence": 39, "accessibility": {"bikesAllowed": "allowed", "wheelchairAccessible": "accessible"}}, {"child_stop_id": "4240", "route_id": "42-10647", "route_code": "42", "service_id": "2023-COMBVAC-Weekday-05", "arrival_time": "PT6H28M0S", "departure_time": "PT6H28M0S", "heading": "Fraser Loop", "sequence": 39, "accessibility": {"bikesAllowed": "allowed", "wheelchairAccessible": "accessible"}}, {"child_stop_id": "4240", "route_id": "42-10647", "route_code": "42", "service_id": "2023-COMBVAC-Weekday-05", "arrival_time": "PT6H58M0S", "departure_time": "PT6H58M0S", "heading": "Fraser Loop", "sequence": 39, "accessibility": {"bikesAllowed": "allowed", "wheelchairAccessible": "accessible"}}, {"child_stop_id": "4240", "route_id": "42-10647", "route_code": "42", "service_id": "2023-COMBVAC-Weekday-05", "arrival_time": "PT7H29M0S", "departure_time": "PT7H29M0S", "heading": "Fraser Loop", "sequence": 39, "accessibility": {"bikesAllowed": "allowed", "wheelchairAccessible": "accessible"}}, {"child_stop_id": "4240", "route_id": "42-10647", "route_code": "42", "service_id": "2023-COMBVAC-Weekday-05", "arrival_time": "PT8H2M0S", "departure_time": "PT8H2M0S", "heading": "Fraser Loop", "sequence": 39, "accessibility": {"bikesAllowed": "allowed", "wheelchairAccessible": "accessible"}}, {"child_stop_id": "4240", "route_id": "42-10647", "route_code": "42", "service_id": "2023-COMBVAC-Weekday-05", "arrival_time": "PT8H32M0S", "departure_time": "PT8H32M0S", "heading": "Fraser Loop", "sequence": 39, "accessibility": {"bikesAllowed": "allowed", "wheelchairAccessible": "accessible"}}, {"child_stop_id": "4240", "route_id": "42-10647", "route_code": "42", "service_id": "2023-COMBVAC-Weekday-05", "arrival_time": "PT9H1M0S", "departure_time": "PT9H1M0S", "heading": "Fraser Loop", "sequence": 39, "accessibility": {"bikesAllowed": "allowed", "wheelchairAccessible": "accessible"}}, {"child_stop_id": "4240", "route_id": "42-10647", "route_code": "42", "service_id": "2023-COMBVAC-Weekday-05", "arrival_time": "PT9H30M0S", "departure_time": "PT9H30M0S", "heading": "Fraser Loop", "sequence": 39, "accessibility": {"bikesAllowed": "allowed", "wheelchairAccessible": "accessible"}}, {"child_stop_id": "4240", "route_id": "42-10647", "route_code": "42", "service_id": "2023-COMBVAC-Weekday-05", "arrival_time": "PT10H1M0S", "departure_time": "PT10H1M0S", "heading": "Fraser Loop", "sequence": 39, "accessibility": {"bikesAllowed": "allowed", "wheelchairAccessible": "accessible"}}, {"child_stop_id": "4240", "route_id": "42-10647", "route_code": "42", "service_id": "2023-COMBVAC-Weekday-05", "arrival_time": "PT10H31M0S", "departure_time": "PT10H31M0S", "heading": "Fraser Loop", "sequence": 39, "accessibility": {"bikesAllowed": "allowed", "wheelchairAccessible": "accessible"}}, {"child_stop_id": "4240", "route_id": "42-10647", "route_code": "42", "service_id": "2023-COMBVAC-Weekday-05", "arrival_time": "PT11H1M0S", "departure_time": "PT11H1M0S", "heading": "Fraser Loop", "sequence": 39, "accessibility": {"bikesAllowed": "allowed", "wheelchairAccessible": "accessible"}}, {"child_stop_id": "4240", "route_id": "42-10647", "route_code": "42", "service_id": "2023-COMBVAC-Weekday-05", "arrival_time": "PT11H31M0S", "departure_time": "PT11H31M0S", "heading": "Fraser Loop", "sequence": 39, "accessibility": {"bikesAllowed": "allowed", "wheelchairAccessible": "accessible"}}, {"child_stop_id": "4240", "route_id": "42-10647", "route_code": "42", "service_id": "2023-COMBVAC-Weekday-05", "arrival_time": "PT12H1M0S", "departure_time": "PT12H1M0S", "heading": "Fraser Loop", "sequence": 39, "accessibility": {"bikesAllowed": "allowed", "wheelchairAccessible": "accessible"}}, {"child_stop_id": "4240", "route_id": "42-10647", "route_code": "42", "service_id": "2023-COMBVAC-Weekday-05", "arrival_time": "PT12H31M0S", "departure_time": "PT12H31M0S", "heading": "Fraser Loop", "sequence": 39, "accessibility": {"bikesAllowed": "allowed", "wheelchairAccessible": "accessible"}}, {"child_stop_id": "4240", "route_id": "42-10647", "route_code": "42", "service_id": "2023-COMBVAC-Weekday-05", "arrival_time": "PT13H1M0S", "departure_time": "PT13H1M0S", "heading": "Fraser Loop", "sequence": 39, "accessibility": {"bikesAllowed": "allowed", "wheelchairAccessible": "accessible"}}, {"child_stop_id": "4240", "route_id": "42-10647", "route_code": "42", "service_id": "2023-COMBVAC-Weekday-05", "arrival_time": "PT13H31M0S", "departure_time": "PT13H31M0S", "heading": "Fraser Loop", "sequence": 39, "accessibility": {"bikesAllowed": "allowed", "wheelchairAccessible": "accessible"}}, {"child_stop_id": "4240", "route_id": "42-10647", "route_code": "42", "service_id": "2023-COMBVAC-Weekday-05", "arrival_time": "PT14H1M0S", "departure_time": "PT14H1M0S", "heading": "Fraser Loop", "sequence": 39, "accessibility": {"bikesAllowed": "allowed", "wheelchairAccessible": "accessible"}}, {"child_stop_id": "4240", "route_id": "42-10647", "route_code": "42", "service_id": "2023-COMBVAC-Weekday-05", "arrival_time": "PT14H31M0S", "departure_time": "PT14H31M0S", "heading": "Fraser Loop", "sequence": 39, "accessibility": {"bikesAllowed": "allowed", "wheelchairAccessible": "accessible"}}, {"child_stop_id": "4240", "route_id": "42-10647", "route_code": "42", "service_id": "2023-COMBVAC-Weekday-05", "arrival_time": "PT15H3M0S", "departure_time": "PT15H3M0S", "heading": "Fraser Loop", "sequence": 39, "accessibility": {"bikesAllowed": "allowed", "wheelchairAccessible": "accessible"}}, {"child_stop_id": "4240", "route_id": "42-10647", "route_code": "42", "service_id": "2023-COMBVAC-Weekday-05", "arrival_time": "PT15H33M0S", "departure_time": "PT15H33M0S", "heading": "Fraser Loop", "sequence": 39, "accessibility": {"bikesAllowed": "allowed", "wheelchairAccessible": "accessible"}}, {"child_stop_id": "4240", "route_id": "42-10647", "route_code": "42", "service_id": "2023-COMBVAC-Weekday-05", "arrival_time": "PT16H3M0S", "departure_time": "PT16H3M0S", "heading": "Fraser Loop", "sequence": 39, "accessibility": {"bikesAllowed": "allowed", "wheelchairAccessible": "accessible"}}, {"child_stop_id": "4240", "route_id": "42-10647", "route_code": "42", "service_id": "2023-COMBVAC-Weekday-05", "arrival_time": "PT16H33M0S", "departure_time": "PT16H33M0S", "heading": "Fraser Loop", "sequence": 39, "accessibility": {"bikesAllowed": "allowed", "wheelchairAccessible": "accessible"}}, {"child_stop_id": "4240", "route_id": "42-10647", "route_code": "42", "service_id": "2023-COMBVAC-Weekday-05", "arrival_time": "PT17H3M0S", "departure_time": "PT17H3M0S", "heading": "Fraser Loop", "sequence": 39, "accessibility": {"bikesAllowed": "allowed", "wheelchairAccessible": "accessible"}}, {"child_stop_id": "4240", "route_id": "42-10647", "route_code": "42", "service_id": "2023-COMBVAC-Weekday-05", "arrival_time": "PT17H33M0S", "departure_time": "PT17H33M0S", "heading": "Fraser Loop", "sequence": 39, "accessibility": {"bikesAllowed": "allowed", "wheelchairAccessible": "accessible"}}, {"child_stop_id": "4240", "route_id": "42-10647", "route_code": "42", "service_id": "2023-COMBVAC-Weekday-05", "arrival_time": "PT18H2M0S", "departure_time": "PT18H2M0S", "heading": "Fraser Loop", "sequence": 39, "accessibility": {"bikesAllowed": "allowed", "wheelchairAccessible": "accessible"}}, {"child_stop_id": "4240", "route_id": "42-10647", "route_code": "42", "service_id": "2023-COMBVAC-Weekday-05", "arrival_time": "PT18H32M0S", "departure_time": "PT18H32M0S", "heading": "Fraser Loop", "sequence": 39, "accessibility": {"bikesAllowed": "unknown", "wheelchairAccessible": "accessible"}}, {"child_stop_id": "4240", "route_id": "42-10647", "route_code": "42", "service_id": "2023-COMBVAC-Weekday-05", "arrival_time": "PT19H2M0S", "departure_time": "PT19H2M0S", "heading": "Fraser Loop", "sequence": 39, "accessibility": {"bikesAllowed": "allowed", "wheelchairAccessible": "accessible"}}, {"child_stop_id": "4240", "route_id": "42-10647", "route_code": "42", "service_id": "2023-COMBVAC-Weekday-05", "arrival_time": "PT19H29M0S", "departure_time": "PT19H29M0S", "heading": "Fraser Loop", "sequence": 39, "accessibility": {"bikesAllowed": "allowed", "wheelchairAccessible": "accessible"}}, {"child_stop_id": "4240", "route_id": "42-10647", "route_code": "42", "service_id": "2023-COMBVAC-Weekday-05", "arrival_time": "PT20H29M0S", "departure_time": "PT20H29M0S", "heading": "Fraser Loop", "sequence": 39, "accessibility": {"bikesAllowed": "allowed", "wheelchairAccessible": "accessible"}}, {"child_stop_id": "4240", "route_id": "42-10647", "route_code": "42", "service_id": "2023-COMBVAC-Weekday-05", "arrival_time": "PT21H29M0S", "departure_time": "PT21H29M0S", "heading": "Fraser Loop", "sequence": 39, "accessibility": {"bikesAllowed": "allowed", "wheelchairAccessible": "accessible"}}, {"child_stop_id": "4240", "route_id": "42-10647", "route_code": "42", "service_id": "2023-COMBVAC-Weekday-05", "arrival_time": "PT22H29M0S", "departure_time": "PT22H29M0S", "heading": "Fraser Loop", "sequence": 39, "accessibility": {"bikesAllowed": "allowed", "wheelchairAccessible": "accessible"}}, {"child_stop_id": "4240", "route_id": "42-10647", "route_code": "42", "service_id": "2023-XMAS24-Mixed-34-0000001", "arrival_time": "PT9H28M0S", "departure_time": "PT9H28M0S", "heading": "Fraser Loop", "sequence": 39, "accessibility": {"bikesAllowed": "unknown", "wheelchairAccessible": "inaccessible"}}, {"child_stop_id": "4240", "route_id": "42-10647", "route_code": "42", "service_id": "2023-XMAS24-Mixed-34-0000001", "arrival_time": "PT11H28M0S", "departure_time": "PT11H28M0S", "heading": "Fraser Loop", "sequence": 39, "accessibility": {"bikesAllowed": "unknown", "wheelchairAccessible": "inaccessible"}}, {"child_stop_id": "4240", "route_id": "42-10647", "route_code": "42", "service_id": "2023-XMAS24-Mixed-34-0000001", "arrival_time": "PT13H28M0S", "departure_time": "PT13H28M0S", "heading": "Fraser Loop", "sequence": 39, "accessibility": {"bikesAllowed": "unknown", "wheelchairAccessible": "inaccessible"}}, {"child_stop_id": "4240", "route_id": "42-10647", "route_code": "42", "service_id": "2023-XMAS24-Mixed-34-0000001", "arrival_time": "PT15H28M0S", "departure_time": "PT15H28M0S", "heading": "Fraser Loop", "sequence": 39, "accessibility": {"bikesAllowed": "unknown", "wheelchairAccessible": "inaccessible"}}]